ntropy_mcp/__init__.py
ntropy_mcp/server.py
ntropy_mcp-0.1.0.dist-info/METADATA
ntropy_mcp-0.1.0.dist-info/WHEEL
ntropy_mcp-0.1.0.dist-info/entry_points.txt
ntropy_mcp-0.1.0.dist-info/RECORD
