Metadata-Version: 2.4
Name: ntropy-mcp
Version: 0.1.0
Summary: MCP server for enriching banking data using the Ntropy API
Author-email: ilia@ntropy.com
Requires-Python: >=3.10
Requires-Dist: mcp>=1.3.0
Requires-Dist: requests
